MANIFEST.in
README.rst
setup.py
camera_calibration/__init__.py
camera_calibration/cmd.py
camera_calibration.egg-info/PKG-INFO
camera_calibration.egg-info/SOURCES.txt
camera_calibration.egg-info/dependency_links.txt
camera_calibration.egg-info/entry_points.txt
camera_calibration.egg-info/requires.txt
camera_calibration.egg-info/top_level.txt
camera_calibration.egg-info/zip-safe