Metadata-Version: 1.0
Name: camera-calibration
Version: 0.1
Summary: A basic script to run camera calibration on images in a folder.
Home-page: https://github.com/IRIM-Technology-Transition-Lab/camera-calibration.git
Author: Michael Sobrepera
Author-email: mjsobrep@live.com
License: License :: OSI Approved :: MIT License
Platform: UNKNOWN
